[
    {
      "id": 0,
      "persons": 2,
      "status": "f",
      "start_time": "45"
    },
    {
      "id": 1,
      "persons": 2,
      "status": "f",
      "start_time": "45"
    },
    {
      "id": 2,
      "persons": 4,
      "status": "f",
      "start_time": "45"
    },
    {
      "id": 3,
      "persons": 4,
      "status": "f",
      "start_time": "45"
    },
    {
      "id": 4,
      "persons": 6,
      "status": "f",
      "start_time": "45"
    },
    {
      "id": 5,
      "persons": 6,
      "status": "f",
      "start_time": "45"
    },
    {
      "id": 6,
      "persons": 8,
      "status": "f",
      "start_time": "45"
    },
    {
      "id": 8,
      "persons": 4,
      "status": "f",
      "start_time": "45"
    },
    {
      "id": 7,
      "persons": 8,
      "status": "f",
      "start_time": "45"
    },
    {
      "id": 8,
      "persons": 2,
      "status": "f",
      "start_time": "45"
    },
    {
      "id": 9,
      "persons": 2,
      "status": "f",
      "start_time": "45"
    }
]